hcaptcha_field/__init__.py
hcaptcha_field/apps.py
hcaptcha_field/fields.py
hcaptcha_field/settings.py
hcaptcha_field/widgets.py
hcaptcha_field/locale/da/LC_MESSAGES/django.mo
hcaptcha_field/locale/da/LC_MESSAGES/django.po
hcaptcha_field/locale/de/LC_MESSAGES/django.mo
hcaptcha_field/locale/de/LC_MESSAGES/django.po
hcaptcha_field/locale/fr/LC_MESSAGES/django.mo
hcaptcha_field/locale/fr/LC_MESSAGES/django.po
hcaptcha_field/locale/nl/LC_MESSAGES/django.mo
hcaptcha_field/locale/nl/LC_MESSAGES/django.po
hcaptcha_field/locale/nl_BE/LC_MESSAGES/django.mo
hcaptcha_field/locale/nl_BE/LC_MESSAGES/django.po
hcaptcha_field/locale/pl/LC_MESSAGES/django.mo
hcaptcha_field/locale/pl/LC_MESSAGES/django.po
hcaptcha_field/templates/hcaptcha_widget.html
django_hcaptcha_field-1.4.0.dist-info/LICENSE
django_hcaptcha_field-1.4.0.dist-info/METADATA
django_hcaptcha_field-1.4.0.dist-info/WHEEL
django_hcaptcha_field-1.4.0.dist-info/top_level.txt
django_hcaptcha_field-1.4.0.dist-info/RECORD
