Metadata-Version: 2.1
Name: django-hcaptcha-field
Version: 1.4.0
Summary: Django hCaptcha Field provides a simple way to protect your Django forms using hCaptcha.
Home-page: https://github.com/tiesjan/django-hcaptcha-field
Author: Ties Jan Hefting
Author-email: hello@tiesjan.com
License: BSD
Project-URL: Bugs, https://github.com/tiesjan/django-hcaptcha-field/issues
Classifier: Development Status :: 5 - Production/Stable
Classifier: Environment :: Web Environment
Classifier: Framework :: Django :: 2.2
Classifier: Framework :: Django :: 3.0
Classifier: Framework :: Django :: 3.1
Classifier: Framework :: Django :: 3.2
Classifier: Framework :: Django :: 4.0
Classifier: Framework :: Django :: 4.1
Classifier: Intended Audience :: Developers
Classifier: License :: OSI Approved :: BSD License
Classifier: Operating System :: OS Independent
Classifier: Programming Language :: Python :: 3.5
Classifier: Programming Language :: Python :: 3.6
Classifier: Programming Language :: Python :: 3.7
Classifier: Programming Language :: Python :: 3.8
Classifier: Programming Language :: Python :: 3.9
Classifier: Programming Language :: Python :: 3.10
Classifier: Topic :: Internet :: WWW/HTTP
Requires-Python: >=3.5
License-File: LICENSE
